pyActigraphy/__init__.py
pyActigraphy/analysis/__init__.py
pyActigraphy/analysis/cosinor.py
pyActigraphy/analysis/flm.py
pyActigraphy/analysis/fractal.py
pyActigraphy/analysis/lids.py
pyActigraphy/analysis/ssa.py
pyActigraphy/filters/__init__.py
pyActigraphy/filters/filters.py
pyActigraphy/filters/sstlog.py
pyActigraphy/io/__init__.py
pyActigraphy/io/base.py
pyActigraphy/io/agd/__init__.py
pyActigraphy/io/agd/agd.py
pyActigraphy/io/atr/__init__.py
pyActigraphy/io/atr/atr.py
pyActigraphy/io/awd/__init__.py
pyActigraphy/io/awd/awd.py
pyActigraphy/io/bba/__init__.py
pyActigraphy/io/bba/bba.py
pyActigraphy/io/dqt/__init__.py
pyActigraphy/io/dqt/dqt.py
pyActigraphy/io/mesa/__init__.py
pyActigraphy/io/mesa/mesa.py
pyActigraphy/io/mtn/__init__.py
pyActigraphy/io/mtn/mtn.py
pyActigraphy/io/reader/__init__.py
pyActigraphy/io/reader/reader.py
pyActigraphy/io/rpx/__init__.py
pyActigraphy/io/rpx/multilang.py
pyActigraphy/io/rpx/rpx.py
pyActigraphy/io/tal/__init__.py
pyActigraphy/io/tal/tal.py
pyActigraphy/light/__init__.py
pyActigraphy/light/gendevice.py
pyActigraphy/light/light.py
pyActigraphy/light/light_metrics.py
pyActigraphy/log/__init__.py
pyActigraphy/log/baselog.py
pyActigraphy/log/sstlog.py
pyActigraphy/mask/__init__.py
pyActigraphy/mask/utils.py
pyActigraphy/metrics/__init__.py
pyActigraphy/metrics/metrics.py
pyActigraphy/profiles/__init__.py
pyActigraphy/profiles/profiles.py
pyActigraphy/recording/__init__.py
pyActigraphy/recording/base.py
pyActigraphy/recording/utils.py
pyActigraphy/reports/__init__.py
pyActigraphy/reports/report.py
pyActigraphy/reports/report_activity.py
pyActigraphy/reports/report_sleep.py
pyActigraphy/reports/utils.py
pyActigraphy/sleep/__init__.py
pyActigraphy/sleep/diary.py
pyActigraphy/sleep/scoring.py
pyActigraphy/sleep/scoring_base.py
pyActigraphy/sleep/sleep.py
pyActigraphy/sleep/scoring/__init__.py
pyActigraphy/sleep/scoring/chronosapiens.py
pyActigraphy/sleep/scoring/csm.py
pyActigraphy/sleep/scoring/roenneberg.py
pyActigraphy-1.2.2.dist-info/LICENSE.md
pyActigraphy-1.2.2.dist-info/METADATA
pyActigraphy-1.2.2.dist-info/WHEEL
pyActigraphy-1.2.2.dist-info/top_level.txt
pyActigraphy-1.2.2.dist-info/RECORD
