Metadata-Version: 2.1
Name: pyActigraphy
Version: 1.2.2
Summary: Analysis package for actigraphy data
Home-page: https://github.com/ghammad/pyActigraphy
Author: Grégory Hammad
Author-email: gregory.hammad@hotmail.fr
License: GNU GPL-3.0
Keywords: actigraphy actimetry analysis python open-source
Classifier: Development Status :: 5 - Production/Stable
Classifier: Intended Audience :: Science/Research
Classifier: Topic :: Scientific/Engineering :: Physics
Classifier: License :: OSI Approved :: GNU General Public License v3 (GPLv3)
Classifier: Programming Language :: Python :: 3
License-File: LICENSE.md
Requires-Dist: joblib
Requires-Dist: lmfit
Requires-Dist: pandas
Requires-Dist: plotly
Requires-Dist: numba
Requires-Dist: numpy
Requires-Dist: pyexcel
Requires-Dist: pyexcel-ods3
Requires-Dist: pyexcel-xlsx
Requires-Dist: scipy
Requires-Dist: spm1d
Requires-Dist: statsmodels (>=0.10)
Requires-Dist: stochastic (>=0.6.0)
Requires-Dist: accelerometer (>=6.2.2)
